social_media/__init__.py
social_media/py.typed
social_media-0.0.0.dist-info/METADATA
social_media-0.0.0.dist-info/WHEEL
social_media-0.0.0.dist-info/licenses/LICENSE
social_media-0.0.0.dist-info/RECORD
